{"fields":[{"isGrouped":false,"type":{"isChoice":true,"asString":"checkbox"},"name":"checkbox","label":"Ich bin damit einverstanden.","isMeta":false,"description":"Das ist der Beschreibungstext von Checkbox","isRequired":true},{"isGrouped":false,"type":{"isChoice":true,"asString":"checkbox"},"name":"checkbox","label":"Ich bin damit einverstanden, dass der hr die von mir im vorstehenden Formular angegebenen personenbezogenen Daten für den Zweck der Kontaktaufnahme mit Upload verarbeitet. Eine Weitergabe an Dritte findet nicht statt, es sei denn, es wird ausdrücklich darauf hingewiesen. Unsere Datenschutzerklärung mit sämtlichen Informationen gemäß Art 13 DSGVO zur Datenverarbeitung durch den hr und zu Ihren Rechten können Sie unter Datenschutzerklärung einsehen. Den Datenschutzbeauftragten des hr erreichen Sie unter datenschutz@hr.de.","isMeta":false,"description":"Das ist der Beschreibungstext von Checkbox","isRequired":true}]}