{
    "@->jsoninclude": "teaser/teasers.inc.json",
    "@->contentpath": "teaser_video_livestream",
    "@->overrides": [
        {
            "@->contentpath": "logicItem.includeModel.teaserSize",
            "@->value": "50"
        },
        {
            "@->contentpath": "logicItem.includeModel.realTeaserSize",
            "@->value": "50"
        },
        {
            "@->contentpath": "logicItem.includeModel.label.byline.context.labelInfo.isPlaysNow",
            "@->value": false
        },
        {
            "@->contentpath": "logicItem.includeModel.label.byline.context.labelInfo.isWillPlay",
            "@->value": true
        }
    ]
}
