{
    "ticker": {
        "type": "ticker",
        "loca": "label_ticker",
        "byline": {
            "bylineSsi": "BylineText aus ssi",
            "bylineText": "BylineText"
        }
    },
    "podcast": {
        "type": "media",
        "loca": "label_podcast",
        "byline": {
            "bylineSsi": "BylineText aus ssi",
            "bylineText": "BylineText"
        }
    },
    "media": {
        "type": "media",
        "loca": "label_media",
        "byline": {
            "bylineSsi": "BylineText aus ssi",
            "bylineText": "BylineText"
        }
    },
    "download": {
        "type": "download",
        "loca": "label_download",
        "byline": {
            "bylineSsi": "ZIP - 3mb",
            "bylineText": "BylineText"
        }
    },
    "event": {
        "type": "event",
        "loca": "label_concert",
        "byline": {
            "bylineSsi": "14.10.22, 20:00 Uhr",
            "bylineText": "BylineText"
        }
    },
    "program": {
        "type": "program",
        "loca": "label_program",
        "byline": {
            "bylineSsi": "14.10.22, 20:00 Uhr",
            "bylineText": "BylineText"
        }
    }
}
